glycresoft-0.4.24.dist-info/RECORD
glycresoft-0.4.24.dist-info/entry_points.txt
glycresoft-0.4.24.dist-info/WHEEL
glycresoft-0.4.24.dist-info/LICENSE
glycresoft-0.4.24.dist-info/top_level.txt
glycresoft-0.4.24.dist-info/METADATA
glycan_profiling/__init__.py
glycresoft/scan_cache.py
glycresoft/symbolic_expression.py
glycresoft/profiler.py
glycresoft/__init__.py
glycresoft/piped_deconvolve.py
glycresoft/version.py
glycresoft/task.py
glycresoft/cli/__main__.py
glycresoft/cli/analyze.py
glycresoft/cli/utils.py
glycresoft/cli/logger_config.py
glycresoft/cli/build_db.py
glycresoft/cli/__init__.py
glycresoft/cli/base.py
glycresoft/cli/mzml.py
glycresoft/cli/export.py
glycresoft/cli/tools.py
glycresoft/cli/config.py
glycresoft/cli/validators.py
glycresoft/plotting/entity_bar_chart.py
glycresoft/plotting/colors.py
glycresoft/plotting/sequence_fragment_logo.py
glycresoft/plotting/summaries.py
glycresoft/plotting/lcms_surface.py
glycresoft/plotting/glycan_visual_classification.py
glycresoft/plotting/diagnostics.py
glycresoft/plotting/spectral_annotation.py
glycresoft/plotting/utils.py
glycresoft/plotting/svg_utils.py
glycresoft/plotting/plot_glycoforms.py
glycresoft/plotting/__init__.py
glycresoft/plotting/map_glycan_network.py
glycresoft/plotting/base.py
glycresoft/plotting/chromatogram_artist.py
glycresoft/plotting/lcms_map.py
glycresoft/chromatogram_tree/mass_shift.py
glycresoft/chromatogram_tree/chromatogram.py
glycresoft/chromatogram_tree/utils.py
glycresoft/chromatogram_tree/generic.py
glycresoft/chromatogram_tree/grouping.py
glycresoft/chromatogram_tree/relation_graph.py
glycresoft/chromatogram_tree/__init__.py
glycresoft/chromatogram_tree/index.py
glycresoft/chromatogram_tree/mass_shift_tree.py
glycresoft/composition_distribution_model/laplacian_smoothing.py
glycresoft/composition_distribution_model/glycome_network_smoothing.py
glycresoft/composition_distribution_model/utils.py
glycresoft/composition_distribution_model/observation.py
glycresoft/composition_distribution_model/prior_distribution.py
glycresoft/composition_distribution_model/constants.py
glycresoft/composition_distribution_model/__init__.py
