Metadata-Version: 2.1
Name: glycresoft
Version: 0.4.24
Summary: Glycan and Glycopeptide Mass Spectrometry Database Search Tool
Author: Joshua Klein
Author-email: jaklein@bu.edu
Project-URL: Documentation, https://mobiusklein.github.io/glycresoft
Project-URL: Source Code, https://github.com/mobiusklein/glycresoft
Project-URL: Issue Tracker, https://github.com/mobiusklein/glycresoft/issues
Classifier: Development Status :: 3 - Alpha
Classifier: Intended Audience :: Science/Research
Classifier: License :: OSI Approved :: Apache Software License
Classifier: Topic :: Scientific/Engineering :: Bio-Informatics
Requires-Python: >3.8
License-File: LICENSE
Requires-Dist: dill>=0.3.5.1
Requires-Dist: six
Requires-Dist: sqlalchemy<1.4.0
Requires-Dist: scipy
Requires-Dist: matplotlib>=3.4.3
Requires-Dist: scikit-learn
Requires-Dist: pyteomics
Requires-Dist: lxml
Requires-Dist: click
Requires-Dist: jinja2>=2.11.1
Requires-Dist: rdflib
Requires-Dist: requests
Requires-Dist: SPARQLWrapper
Requires-Dist: ms-deisotope>=0.0.55
Requires-Dist: glypy>=1.0.6
Requires-Dist: glycopeptidepy>=0.0.28
Requires-Dist: brain-isotopic-distribution>=1.5.8
Requires-Dist: ms-peak-picker>=0.1.46
Requires-Dist: python-idzip>=0.3.2
Requires-Dist: pyzstd
Requires-Dist: numpy; python_version < "3.9"
Requires-Dist: numpy>=2.0.0; python_version >= "3.9"
Provides-Extra: fragmentation-modeling
Requires-Dist: glycopeptide-feature-learning; extra == "fragmentation-modeling"
